cream/__init__.py
cream/engine/__init__.py
cream/engine/deeplearning.py
cream/functions/__init__.py
cream/functions/activation.py
cream/functions/function.py
cream/layer/__init__.py
cream/layer/dense.py
cream/layer/dropout.py
cream/layer/flatten.py
cream/tool/__init__.py
cream/tool/colors.py
cream/tool/csys.py
cream/tool/datasets.py
cream/tool/progress_bar.py
pycream-1.0.4.dist-info/METADATA
pycream-1.0.4.dist-info/WHEEL
pycream-1.0.4.dist-info/top_level.txt
pycream-1.0.4.dist-info/RECORD
